examples/__init__.py
examples/empty.py
examples/account_status_rules/__init__.py
examples/account_status_rules/main.py
examples/account_status_rules/rule_based_block_rules.py
examples/kitchen_sink/__init__.py
examples/kitchen_sink/lending_rules.py
examples/kitchen_sink/rules.py
examples/kitchen_sink/rules_nested.py
examples/kitchen_sink/runner.py
examples/kitchen_sink/runner_with_api.py
ruleau/__init__.py
ruleau/adapter.py
ruleau/aggregates.py
ruleau/constants.py
ruleau/context_manager.py
ruleau/decorators.py
ruleau/doc_parsers.py
ruleau/docs.py
ruleau/documentation_enrichment_functions.py
ruleau/exceptions.py
ruleau/execute.py
ruleau/process.py
ruleau/rule.py
ruleau/types.py
ruleau/html/documentation.html
ruleau/structures/__init__.py
ruleau/structures/common_structures.py
ruleau/structures/execution_result.py
ruleau/structures/org_data_models.py
ruleau/structures/ruleau_dict.py
tests/test_data/__init__.py
tests/test_data/broken_import.py
tests/test_data/not_a_rule.py
tests/test_data/relative_referenced_rules.py
tests/test_data/top_level_referenced_rules.py
tests/test_data/shared_rules/__init__.py
tests/test_data/shared_rules/rules.py
ruleau-0.7.1.dist-info/LICENSE
ruleau-0.7.1.dist-info/METADATA
ruleau-0.7.1.dist-info/WHEEL
ruleau-0.7.1.dist-info/entry_points.txt
ruleau-0.7.1.dist-info/top_level.txt
ruleau-0.7.1.dist-info/RECORD
