Metadata-Version: 2.1
Name: ruleau
Version: 0.7.1
Summary: A python rules engine
Home-page: https://gitlab.com/unai-ltd/unai-decision/ruleau-core
Author: Unai Ltd
Author-email: pypi@unai.com
License: BSD 3-Clause
Classifier: Programming Language :: Python :: 3
Classifier: License :: OSI Approved :: BSD License
Classifier: Operating System :: OS Independent
Requires-Python: >=3.6.8
License-File: LICENSE
Requires-Dist: flatdict (==4.0.1)
Requires-Dist: Jinja2 (==3.0.3)
Requires-Dist: jsonpath-ng (==1.5.2)
Requires-Dist: regex (==2021.4.4)
Requires-Dist: requests (==2.25.1)
Requires-Dist: pyjwt (==2.3.0)
